process_boss/__init__.py
process_boss/__main__.py
process_boss/domain/Config.py
process_boss/domain/State.py
process_boss/domain/__init__.py
process_boss/domain/config/Logs.py
process_boss/domain/config/Processes.py
process_boss/domain/config/Scheduler.py
process_boss/domain/config/__init__.py
process_boss/domain/config/processes/Process.py
process_boss/domain/config/processes/__init__.py
process_boss/domain/config/scheduler/Loop.py
process_boss/domain/config/scheduler/__init__.py
process_boss/domain/state/Process.py
process_boss/domain/state/__init__.py
process_boss/service/ProcessScheduler.py
process_boss/service/__init__.py
process_boss/util/ConfigHandler.py
process_boss/util/FileHandler.py
process_boss/util/LogHandler.py
process_boss/util/__init__.py
process_boss-0.0.6.dist-info/LICENSE
process_boss-0.0.6.dist-info/METADATA
process_boss-0.0.6.dist-info/WHEEL
process_boss-0.0.6.dist-info/top_level.txt
process_boss-0.0.6.dist-info/RECORD
