Metadata-Version: 2.1
Name: process_boss
Version: 0.0.6
Summary: A python implementation of a cron job scheduler
Author: kristof9851
Project-URL: Homepage, https://github.com/kristof9851/process_boss
Project-URL: Issues, https://github.com/kristof9851/process_boss/issues
Classifier: Topic :: Software Development :: Libraries :: Python Modules
Classifier: Intended Audience :: Developers
Classifier: Programming Language :: Python
Classifier: Programming Language :: Python :: 3.10
Classifier: License :: OSI Approved :: MIT License
Requires-Python: >=3.10
License-File: LICENSE
